[
  {
    "name": "أجناد",
    "cover_url": "https://k.top4top.io/p_3616msih40.jpg"
  },
  {
    "name": "أصداء",
    "cover_url": "https://e.top4top.io/p_3616s5noa0.jpg"
  },
  {
    "name": "ألبيان",
    "cover_url": "https://f.top4top.io/p_3616q0uhd0.jpg"
  },
  {
    "name": "الأنصار",
    "cover_url": "https://g.top4top.io/p_3616qvmpw0.jpg"
  },
  {
    "name": "ألذكرى",
    "cover_url": "https://i.top4top.io/p_3616vlzta0.jpg"
  },
  {
    "name": "Foreign",
    "cover_url": "https://l.top4top.io/p_3616en30x0.jpg"
  }
]
